stglance/__init__.py
stglance/ml_explorer.py
stglance/stglance.py
stglance/tests/__init__.py
stglance-0.1.4.dist-info/WHEEL
stglance-0.1.4.dist-info/METADATA
stglance-0.1.4.dist-info/RECORD
